{
  "id": "infinitys-edge",
  "title": "Infinity's Edge",
  "description": "The Infinity's Edge system for FoundryVTT!",
  "authors": [
    {
      "name": "Tyler Meador"
    }
  ],
  "url": "https://github.com/Tyler-Meador/infinitys-edge",
  "license": "LICENSE.txt",
  "readme": "README.md",
  "bugs": "",
  "changelog": "CHANGELOG.md",
  "media": [
    {
      "type": "setup",
      "url": "systems/infinitys-edge/assets/anvil-impact.png",
      "thumbnail": "systems/infinitys-edge/assets/anvil-impact.png"
    }
  ],
  "version": "0.0.1",
  "compatibility": {
    "minimum": 12
  },
  "esmodules": ["module/infinitys-edge.mjs"],
  "styles": ["css/infinitys-edge.css"],
  "languages": [
    {
      "lang": "en",
      "name": "English",
      "path": "lang/en.json"
    }
  ],
  "packs": [],
  "packFolders": [],
  "socket": false,
  "manifest": "Replace this with a link to the /latest release system.json so people can receive updates after they've installed the system",
  "download": "This must link to a .zip file of the current version",
  "background": "systems/infinitys-edge/assets/anvil-impact.png",
  "gridDistance": 5,
  "gridUnits": "ft",
  "primaryTokenAttribute": "health",
  "secondaryTokenAttribute": "stamina"
}
